README.rst
setup.py
nose_focus/__init__.py
nose_focus/plugin.py
nose_focus.egg-info/PKG-INFO
nose_focus.egg-info/SOURCES.txt
nose_focus.egg-info/dependency_links.txt
nose_focus.egg-info/entry_points.txt
nose_focus.egg-info/requires.txt
nose_focus.egg-info/top_level.txt