Metadata-Version: 1.0
Name: nose-focus
Version: 0.1
Summary: Decorator and plugin to make nose focus on specific tests
Home-page: http://nose_focus.readthedocs.org
Author: Stephen Moore
Author-email: stephen@delfick.com
License: WTFPL
Keywords: nose tests focus
Platform: UNKNOWN
